Workbook

Sheet Overview
A1: Emigrant Wilderness — Big Sam Loop Crew Meal Plan (19 People)
A2: July 25–30, 2026 · Kennedy Meadows Loop · ~46.9 mi · 13 Scouts · 6 Adults | 3 Scout cans (3 people) · 1 Scout can (4 people) · 2 Adult cans (3 people)
A4: BEAR CAN STRUCTURE
A5: Can assignment | B5: Can 1 | C5: Can 2 | D5: Can 3 | E5: Can 4 | F5: Can 5 | G5: Can 6 | H5: Type | I5: People | J5: Notes
A6: Can assignment | B6: Scout Can 1 | C6: Scout Can 2 | D6: Scout Can 3 | E6: Scout Can 4 | F6: Adult Can 1 | G6: Adult Can 2 | J6: 4 scout cans + 2 adult cans
A7: People per can | B7: 3 scouts | C7: 3 scouts | D7: 3 scouts | E7: 4 scouts | F7: 3 adults | G7: 3 adults | J7: Scouts: 3, 3, 3, 4 · Adults: 3, 3
A8: Hot drink | B8: Swiss Miss | C8: Swiss Miss | D8: Swiss Miss | E8: Swiss Miss | F8: own coffee | G8: own coffee | J8: Scouts: Swiss Miss · Adults: own coffee/tea
A9: Carry capacity | B9: 3 Days | C9: 3 Days | D9: 3 Days | E9: 3 Days | F9: 3 Days | G9: 3 Days | J9: Balance food is mule dropped (Days 4–6)
A11: TRIP SCHEDULE
A12: Day | B12: Date | C12: Route | D12: Miles | E12: Gain | F12: Loss | G12: Camp | H12: Meals | I12: Water | J12: Notes
A13: Day 1 | B13: Sat Jul 25 | C13: Kennedy Meadows → Lower Relief Valley | D13: 6.88 mi | E13: +2,262 ft | F13: −579 ft | G13: Lower Relief Valley | H13: Snacks · Lunch · Dinner · Dessert | I13: Reservoir/Creek (filter) | J13: morale swimming hole side-trip
A14: Day 2 | B14: Sun Jul 26 | C14: Lower Relief Valley → Spring Meadow | D14: 5.97 mi | E14: +1,129 ft | F14: −509 ft | G14: Spring Meadow | H14: Bkfst · Snacks · Lunch · Dinner · Dessert | I14: Spring/Creek (filter) | J14: Wire Lake side-trip
A15: Day 3 | B15: Mon Jul 27 | C15: Spring Meadow → eastern Emigrant Lake | D15: 8.89 mi | E15: +1,210 ft | F15: −1,035 ft | G15: Emigrant Lake (east) | H15: Bkfst · Snacks · Lunch · Dinner · Dessert | I15: Lake (filter) | J15: morale swimming spot; Buck Lake on route
A16: Day 4 | B16: Tue Jul 28 | C16: Emigrant Lake → Grizzly Peak Base Camp | D16: 6.59 mi | E16: +1,575 ft | F16: −742 ft | G16: Grizzly Peak Base Camp | H16: Bkfst · Snacks · Lunch · Dinner · Dessert | I16: Lake (filter) | J16: Mule drop refilled; cooler alpine camp
A17: Day 5 | B17: Wed Jul 29 | C17: Grizzly Peak → Big Sam → Kennedy Lake | D17: 8.46 mi | E17: +1,428 ft | F17: −3,238 ft | G17: South Kennedy Lake | H17: Bkfst · Snacks · Lunch · Dinner · Dessert | I17: Creek (filter) | J17: Climb Big Sam (10,804 ft); long descent
A18: Day 6 | B18: Thu Jul 30 | C18: Kennedy Lake → Kennedy Meadows (Exit) | D18: 8.50 mi | E18: +0 ft | F18: −1,517 ft | G18: Exit — Trailhead | H18: Bkfst · Snacks · Lunch | I18: Creek/Tap | J18: Walk out valley; celebrate at trailhead
A19: TOTALS | D19: 51.29 mi | E19: +7,604 ft | F19: −8,620 ft | J19: Totals include optional side-trips
A21: CALORIE OVERVIEW (per person)
B22: Scouts | C22: Adults | D22: Notes
A23: Target (full active day) | B23: ~2,750 kcal | C23: ~3,750 kcal | D23: Target calorie values
A24: Sat Jul 25 delivered | B24: ='Meal Plan (Per Bear Can)'!F31 | C24: ='Meal Plan (Per Bear Can)'!H31 | D24: Snacks + Lunch + Dinner + Dessert (no breakfast carried)
A25: Sun Jul 26 delivered | B25: ='Meal Plan (Per Bear Can)'!F72 | C25: ='Meal Plan (Per Bear Can)'!H72 | D25: Bkfst + Snacks + Lunch + Dinner + Dessert + Adult Supp
A26: Mon Jul 27 delivered | B26: ='Meal Plan (Per Bear Can)'!F108 | C26: ='Meal Plan (Per Bear Can)'!H108 | D26: Bkfst + Snacks + Lunch + Dinner + Dessert
A27: Tue Jul 28 delivered | B27: ='Meal Plan (Per Bear Can)'!F144 | C27: ='Meal Plan (Per Bear Can)'!H144 | D27: Bkfst + Snacks + Lunch + Dinner + Dessert
A28: Wed Jul 29 delivered | B28: ='Meal Plan (Per Bear Can)'!F186 | C28: ='Meal Plan (Per Bear Can)'!H186 | D28: Bkfst + Snacks + Lunch + Dinner + Dessert + Adult Supp
A29: Thu Jul 30 delivered | B29: ='Meal Plan (Per Bear Can)'!F210 | C29: ='Meal Plan (Per Bear Can)'!H210 | D29: Bkfst + Snacks + Lunch (exit day; no dinner)
A30: TRIP TOTAL (6 DAYS) | B30: ='Meal Plan (Per Bear Can)'!F215 | C30: ='Meal Plan (Per Bear Can)'!H215 | D30: Total food purchased per person across all 6 days
A31: MAX CARRY WEIGHT VOL (3 DAYS) | B31: =MAX('Meal Plan (Per Bear Can)'!F110,'Meal Plan (Per Bear Can)'!F212) | C31: =MAX('Meal Plan (Per Bear Can)'!H110,'Meal Plan (Per Bear Can)'!H212) | D31: Maximum food carried at one time in canisters
A33: BUDGET & WEIGHT OVERVIEW (6 Days Purchased / 3 Days Carried)
B34: Adult Can (3 ppl) (×2) | C34: Scout Can (3 ppl) (×3) | D34: Scout Can (4 ppl) (×1) | E34: Group Total | F34: Notes
A35: Estimated Purchased Cost (6 days) | B35: =SUM('Shopping List'!M$4:M$32) | C35: =SUM('Shopping List'!K$4:K$32) | D35: =SUM('Shopping List'!L$4:L$32) | E35: =SUM('Shopping List'!N$4:N$32) | F35: Full 6 days food cost; bulk prices
A36: Per person cost | B36: =B35/3 | C36: =C35/3 | D36: =D35/4 | E36: =E35/19 | F36: Averaged across group
A37: Max Carry Weight (3 days) | B37: =SUMPRODUCT('Shopping List'!E$4:E$32,'Shopping List'!O$4:O$32)/16 | C37: =SUMPRODUCT('Shopping List'!C$4:C$32,'Shopping List'!O$4:O$32)/16 | D37: =SUMPRODUCT('Shopping List'!D$4:D$32,'Shopping List'!O$4:O$32)/16 | E37: =SUMPRODUCT(3*'Shopping List'!C$4:C$32+1*'Shopping List'!D$4:D$32+2*'Shopping List'!E$4:E$32,'Shopping List'!O$4:O$32)/16 | F37: Max carried weight in lbs (Phase 1)
A38: Mule Drop Weight (3 days) | B38: =SUMPRODUCT('Shopping List'!H$4:H$32,'Shopping List'!O$4:O$32)/16 | C38: =SUMPRODUCT('Shopping List'!F$4:F$32,'Shopping List'!O$4:O$32)/16 | D38: =SUMPRODUCT('Shopping List'!G$4:G$32,'Shopping List'!O$4:O$32)/16 | E38: =SUMPRODUCT(3*'Shopping List'!F$4:F$32+1*'Shopping List'!G$4:G$32+2*'Shopping List'!H$4:H$32,'Shopping List'!O$4:O$32)/16 | F38: Mule drop weight in lbs (Phase 2)
A40: WATER & SAFETY INFORMATION
A41: Location | B41: Source | C41: Reliability | D41: Required Action
A42: Kennedy Meadows Trailhead | B42: Pack Station tap | C42: Reliable | D42: Fill all bottles. Carry 2-3 L per person.
A43: Relief Reservoir | B43: Reservoir outlet | C43: Reliable | D43: morale boost lunch stop. Filter all water.
A44: Lower Relief Valley Camp | B44: Creek / Spring | C44: Reliable | D44: morale swimming spot side trip nearby.
A45: Spring Meadow Camp | B45: Meadow stream | C45: Reliable | D45: morale boost meadow camp. Filter water.
A46: Emigrant Lake Camp | B46: Lake water | C46: Reliable | D46: Marquee camp. Swim spot. Filter before drinking.
A47: Grizzly Peak Base Camp | B47: Alpine lake | C47: Reliable | D47: High alpine water. Cooler nights. Filter.
A48: Kennedy Lake Camp | B48: Kennedy Creek | C48: Reliable | D48: morale swimming spot. Filter.
A49: Kennedy Meadows Exit | B49: Pack Station tap | C49: Reliable | D49: morale boost finish. Walk out valley.

Sheet Meal Plan (Per Bear Can)
A1: Meal Plan — Quantities & Nutritional Breakdown Per Bear Can Type
A2: Calculated for: Scout Can (3 people), Scout Can (4 people), and Adult Can (3 people) | ⚠ Highlighted = Contains Nuts (swap for allergy scout)
A4: PHASE 1 — INITIAL CARRY (DAYS 1–3)
A5: SAT JUL 25 — DAY 1 DETAILS
A6: Sat Jul 25 — BREAKFAST (✗ NOT CARRIED — eat before leaving trailhead)
A7: Sat Jul 25 — SNACKS
A8: Food Item | B8: Qty (Scout 3) | C8: Qty (Scout 4) | D8: Qty (Adult 3) | E8: kcal/unit | F8: Scout 3 kcal | G8: Scout 4 kcal | H8: Adult 3 kcal | I8: $/unit | J8: Scout 3 $ | K8: Scout 4 $ | L8: Adult 3 $ | M8: oz/unit | N8: Scout 3 oz | O8: Scout 4 oz | P8: Adult 3 oz | Q8: Notes
A9: Kind – Peanut Butter Dark Chocolate Bar | B9: 3 | C9: 4 | D9: 3 | E9: 200 | F9: =B9*E9 | G9: =C9*E9 | H9: =D9*E9 | I9: 1.04 | J9: =B9*I9 | K9: =C9*I9 | L9: =D9*I9 | M9: 1.4 | N9: =B9*M9 | O9: =C9*M9 | P9: =D9*M9 | Q9: ⚠ NUT: swap → 88 Acres bar
A10: Kind – Caramel Almond & Peanut Bar | B10: 3 | C10: 4 | D10: 3 | E10: 180 | F10: =B10*E10 | G10: =C10*E10 | H10: =D10*E10 | I10: 1.59 | J10: =B10*I10 | K10: =C10*I10 | L10: =D10*I10 | M10: 1.4 | N10: =B10*M10 | O10: =C10*M10 | P10: =D10*M10 | Q10: ⚠ NUT: swap → 88 Acres bar
A11: Krave Sea Salt Original Beef Jerky | B11: 3 | C11: 4 | D11: 3 | E11: 140 | F11: =B11*E11 | G11: =C11*E11 | H11: =D11*E11 | I11: 2.19 | J11: =B11*I11 | K11: =C11*I11 | L11: =D11*I11 | M11: 1.48 | N11: =B11*M11 | O11: =C11*M11 | P11: =D11*M11 | Q11: Safe for nut allergy ✓
A12: Gatorade Powder Pack | B12: 3 | C12: 4 | D12: 3 | E12: 130 | F12: =B12*E12 | G12: =C12*E12 | H12: =D12*E12 | I12: 0.38 | J12: =B12*I12 | K12: =C12*I12 | L12: =D12*I12 | M12: 1.23 | N12: =B12*M12 | O12: =C12*M12 | P12: =D12*M12 | Q12: Electrolytes
A13: Trader Joe's Dried Mango Slices (1 oz) | B13: 3 | C13: 4 | D13: 3 | E13: 90 | F13: =B13*E13 | G13: =C13*E13 | H13: =D13*E13 | I13: 0.55 | J13: =B13*I13 | K13: =C13*I13 | L13: =D13*I13 | M13: 1 | N13: =B13*M13 | O13: =C13*M13 | P13: =D13*M13 | Q13: TJ's — Sat snack · nut-free ✓
A14: SNACKS Total | F14: =SUM(F9:F13) | G14: =SUM(G9:G13) | H14: =SUM(H9:H13) | J14: =SUM(J9:J13) | K14: =SUM(K9:K13) | L14: =SUM(L9:L13) | N14: =SUM(N9:N13) | O14: =SUM(O9:O13) | P14: =SUM(P9:P13)
A15: Sat Jul 25 — LUNCH
A16: Food Item | B16: Qty (Scout 3) | C16: Qty (Scout 4) | D16: Qty (Adult 3) | E16: kcal/unit | F16: Scout 3 kcal | G16: Scout 4 kcal | H16: Adult 3 kcal | I16: $/unit | J16: Scout 3 $ | K16: Scout 4 $ | L16: Adult 3 $ | M16: oz/unit | N16: Scout 3 oz | O16: Scout 4 oz | P16: Adult 3 oz | Q16: Notes
A17: ProBar Meal – Oatmeal Chocolate Chip | B17: 3 | C17: 4 | D17: 3 | E17: 290 | F17: =B17*E17 | G17: =C17*E17 | H17: =D17*E17 | I17: 2.99 | J17: =B17*I17 | K17: =C17*I17 | L17: =D17*I17 | M17: 3 | N17: =B17*M17 | O17: =C17*M17 | P17: =D17*M17 | Q17: Lunch · ⚠ NUT (cashews)
A18: LUNCH Total | F18: =SUM(F17:F17) | G18: =SUM(G17:G17) | H18: =SUM(H17:H17) | J18: =SUM(J17:J17) | K18: =SUM(K17:K17) | L18: =SUM(L17:L17) | N18: =SUM(N17:N17) | O18: =SUM(O17:O17) | P18: =SUM(P17:P17)
A19: Sat Jul 25 — DINNER
A20: Food Item | B20: Qty (Scout 3) | C20: Qty (Scout 4) | D20: Qty (Adult 3) | E20: kcal/unit | F20: Scout 3 kcal | G20: Scout 4 kcal | H20: Adult 3 kcal | I20: $/unit | J20: Scout 3 $ | K20: Scout 4 $ | L20: Adult 3 $ | M20: oz/unit | N20: Scout 3 oz | O20: Scout 4 oz | P20: Adult 3 oz | Q20: Notes
A21: Peak Refuel – Beef Pasta Marinara | B21: 2 | C21: 3 | D21: 3 | E21: 780 | F21: =B21*E21 | G21: =C21*E21 | H21: =D21*E21 | I21: 7.49 | J21: =B21*I21 | K21: =C21*I21 | L21: =D21*I21 | M21: 3.2 | N21: =B21*M21 | O21: =C21*M21 | P21: =D21*M21 | Q21: Sat dinner (1.5 svgs/pouch)
A22: Mission Street Taco Flour Tortillas | B22: 6 | C22: 8 | D22: 6 | E22: 75 | F22: =B22*E22 | G22: =C22*E22 | H22: =D22*E22 | I22: 0.25 | J22: =B22*I22 | K22: =C22*I22 | L22: =D22*I22 | M22: 0.5 | N22: =B22*M22 | O22: =C22*M22 | P22: =D22*M22 | Q22: 2/person; nut-free ✓
A23: Tillamook Cheddar Cheese Packets | B23: 6 | C23: 8 | D23: 6 | E23: 90 | F23: =B23*E23 | G23: =C23*E23 | H23: =D23*E23 | I23: 0.75 | J23: =B23*I23 | K23: =C23*I23 | L23: =D23*I23 | M23: 0.7 | N23: =B23*M23 | O23: =C23*M23 | P23: =D23*M23 | Q23: 2/person; nut-free ✓
A24: Swiss Miss Hot Chocolate | B24: 6 | C24: 8 | D24: 0 | E24: 90 | F24: =B24*E24 | G24: =C24*E24 | H24: =D24*E24 | I24: 0.38 | J24: =B24*I24 | K24: =C24*I24 | L24: =D24*I24 | M24: 0.73 | N24: =B24*M24 | O24: =C24*M24 | P24: =D24*M24 | Q24: Scouts only (2 packets/person)
A25: DINNER Total | F25: =SUM(F21:F24) | G25: =SUM(G21:G24) | H25: =SUM(H21:H24) | J25: =SUM(J21:J24) | K25: =SUM(K21:K24) | L25: =SUM(L21:L24) | N25: =SUM(N21:N24) | O25: =SUM(O21:O24) | P25: =SUM(P21:P24)
A26: Sat Jul 25 — DESSERT
A27: Food Item | B27: Qty (Scout 3) | C27: Qty (Scout 4) | D27: Qty (Adult 3) | E27: kcal/unit | F27: Scout 3 kcal | G27: Scout 4 kcal | H27: Adult 3 kcal | I27: $/unit | J27: Scout 3 $ | K27: Scout 4 $ | L27: Adult 3 $ | M27: oz/unit | N27: Scout 3 oz | O27: Scout 4 oz | P27: Adult 3 oz | Q27: Notes
A28: Backpacker's Pantry – Crème Brûlée | B28: 2 | C28: 2 | D28: 2 | E28: 620 | F28: =B28*E28 | G28: =C28*E28 | H28: =D28*E28 | I28: 8.99 | J28: =B28*I28 | K28: =C28*I28 | L28: =D28*I28 | M28: 2.26 | N28: =B28*M28 | O28: =C28*M28 | P28: =D28*M28 | Q28: Buddy-pair shares pouch
A29: Swiss Miss Hot Chocolate | B29: 6 | C29: 8 | D29: 0 | E29: 90 | F29: =B29*E29 | G29: =C29*E29 | H29: =D29*E29 | I29: 0.38 | J29: =B29*I29 | K29: =C29*I29 | L29: =D29*I29 | M29: 0.73 | N29: =B29*M29 | O29: =C29*M29 | P29: =D29*M29 | Q29: Scouts only (2 packets/person)
A30: DESSERT Total | F30: =SUM(F28:F29) | G30: =SUM(G28:G29) | H30: =SUM(H28:H29) | J30: =SUM(J28:J29) | K30: =SUM(K28:K29) | L30: =SUM(L28:L29) | N30: =SUM(N28:N29) | O30: =SUM(O28:O29) | P30: =SUM(P28:P29)
A31: DAY 1 (Sat Jul 25) TOTAL | F31: =SUM(F14,F18,F25,F30) | G31: =SUM(G14,G18,G25,G30) | H31: =SUM(H14,H18,H25,H30) | J31: =SUM(J14,J18,J25,J30) | K31: =SUM(K14,K18,K25,K30) | L31: =SUM(L14,L18,L25,L30) | N31: =SUM(N14,N18,N25,N30) | O31: =SUM(O14,O18,O25,O30) | P31: =SUM(P14,P18,P25,P30)
A33: SUN JUL 26 — DAY 2 DETAILS
A34: Sun Jul 26 — BREAKFAST
A35: Food Item | B35: Qty (Scout 3) | C35: Qty (Scout 4) | D35: Qty (Adult 3) | E35: kcal/unit | F35: Scout 3 kcal | G35: Scout 4 kcal | H35: Adult 3 kcal | I35: $/unit | J35: Scout 3 $ | K35: Scout 4 $ | L35: Adult 3 $ | M35: oz/unit | N35: Scout 3 oz | O35: Scout 4 oz | P35: Adult 3 oz | Q35: Notes
A36: MET-Rx Big100 – Super Cookie Crunch | B36: 3 | C36: 4 | D36: 3 | E36: 410 | F36: =B36*E36 | G36: =C36*E36 | H36: =D36*E36 | I36: 2.19 | J36: =B36*I36 | K36: =C36*I36 | L36: =D36*I36 | M36: 3.53 | N36: =B36*M36 | O36: =C36*M36 | P36: =D36*M36 | Q36: Bkfst · ⚠ NUT
A37: Swiss Miss Hot Chocolate | B37: 6 | C37: 8 | D37: 0 | E37: 90 | F37: =B37*E37 | G37: =C37*E37 | H37: =D37*E37 | I37: 0.38 | J37: =B37*I37 | K37: =C37*I37 | L37: =D37*I37 | M37: 0.73 | N37: =B37*M37 | O37: =C37*M37 | P37: =D37*M37 | Q37: Scouts only (2 packets/person)
A38: Adults: own coffee / tea | B38: 0 | C38: 0 | D38: 3 | E38: 0 | F38: =B38*E38 | G38: =C38*E38 | H38: =D38*E38 | I38: 0 | J38: =B38*I38 | K38: =C38*I38 | L38: =D38*I38 | M38: 0 | N38: =B38*M38 | O38: =C38*M38 | P38: =D38*M38 | Q38: Adults only ★
A39: BREAKFAST Total | F39: =SUM(F36:F38) | G39: =SUM(G36:G38) | H39: =SUM(H36:H38) | J39: =SUM(J36:J38) | K39: =SUM(K36:K38) | L39: =SUM(L36:L38) | N39: =SUM(N36:N38) | O39: =SUM(O36:O38) | P39: =SUM(P36:P38)
A40: Sun Jul 26 — SNACKS
A41: Food Item | B41: Qty (Scout 3) | C41: Qty (Scout 4) | D41: Qty (Adult 3) | E41: kcal/unit | F41: Scout 3 kcal | G41: Scout 4 kcal | H41: Adult 3 kcal | I41: $/unit | J41: Scout 3 $ | K41: Scout 4 $ | L41: Adult 3 $ | M41: oz/unit | N41: Scout 3 oz | O41: Scout 4 oz | P41: Adult 3 oz | Q41: Notes
A42: Krave Sea Salt Original Beef Jerky | B42: 3 | C42: 4 | D42: 3 | E42: 140 | F42: =B42*E42 | G42: =C42*E42 | H42: =D42*E42 | I42: 2.19 | J42: =B42*I42 | K42: =C42*I42 | L42: =D42*I42 | M42: 1.48 | N42: =B42*M42 | O42: =C42*M42 | P42: =D42*M42 | Q42: Safe for nut allergy ✓
A43: Kind – Dark Choc Nuts & Sea Salt Bar | B43: 3 | C43: 4 | D43: 3 | E43: 200 | F43: =B43*E43 | G43: =C43*E43 | H43: =D43*E43 | I43: 1.04 | J43: =B43*I43 | K43: =C43*I43 | L43: =D43*I43 | M43: 1.4 | N43: =B43*M43 | O43: =C43*M43 | P43: =D43*M43 | Q43: ⚠ NUT: swap → 88 Acres bar
A44: Gatorade Powder Pack | B44: 6 | C44: 8 | D44: 6 | E44: 130 | F44: =B44*E44 | G44: =C44*E44 | H44: =D44*E44 | I44: 0.38 | J44: =B44*I44 | K44: =C44*I44 | L44: =D44*I44 | M44: 1.23 | N44: =B44*M44 | O44: =C44*M44 | P44: =D44*M44 | Q44: ×2/person; climb day
A45: Banana Chips (1 oz) | B45: 3 | C45: 4 | D45: 3 | E45: 100 | F45: =B45*E45 | G45: =C45*E45 | H45: =D45*E45 | I45: 0.45 | J45: =B45*I45 | K45: =C45*I45 | L45: =D45*I45 | M45: 1 | N45: =B45*M45 | O45: =C45*M45 | P45: =D45*M45 | Q45: Nut-free ✓
A46: SNACKS Total | F46: =SUM(F42:F45) | G46: =SUM(G42:G45) | H46: =SUM(H42:H45) | J46: =SUM(J42:J45) | K46: =SUM(K42:K45) | L46: =SUM(L42:L45) | N46: =SUM(N42:N45) | O46: =SUM(O42:O45) | P46: =SUM(P42:P45)
A47: Sun Jul 26 — LUNCH
A48: Food Item | B48: Qty (Scout 3) | C48: Qty (Scout 4) | D48: Qty (Adult 3) | E48: kcal/unit | F48: Scout 3 kcal | G48: Scout 4 kcal | H48: Adult 3 kcal | I48: $/unit | J48: Scout 3 $ | K48: Scout 4 $ | L48: Adult 3 $ | M48: oz/unit | N48: Scout 3 oz | O48: Scout 4 oz | P48: Adult 3 oz | Q48: Notes
A49: Chicken of the Sea Shredded Chicken Pouch | B49: 3 | C49: 4 | D49: 3 | E49: 70 | F49: =B49*E49 | G49: =C49*E49 | H49: =D49*E49 | I49: 2.29 | J49: =B49*I49 | K49: =C49*I49 | L49: =D49*I49 | M49: 2.5 | N49: =B49*M49 | O49: =C49*M49 | P49: =D49*M49 | Q49: No cook; nut-free ✓
A50: Mission Street Taco Flour Tortillas | B50: 6 | C50: 8 | D50: 6 | E50: 75 | F50: =B50*E50 | G50: =C50*E50 | H50: =D50*E50 | I50: 0.25 | J50: =B50*I50 | K50: =C50*I50 | L50: =D50*I50 | M50: 0.5 | N50: =B50*M50 | O50: =C50*M50 | P50: =D50*M50 | Q50: 2/person; nut-free ✓
A51: Tillamook Cheddar Cheese Packets | B51: 3 | C51: 4 | D51: 3 | E51: 90 | F51: =B51*E51 | G51: =C51*E51 | H51: =D51*E51 | I51: 0.75 | J51: =B51*I51 | K51: =C51*I51 | L51: =D51*I51 | M51: 0.7 | N51: =B51*M51 | O51: =C51*M51 | P51: =D51*M51 | Q51: 1/person; nut-free ✓
A52: Clif Bar – Crunchy PB | B52: 3 | C52: 4 | D52: 3 | E52: 250 | F52: =B52*E52 | G52: =C52*E52 | H52: =D52*E52 | I52: 1.29 | J52: =B52*I52 | K52: =C52*I52 | L52: =D52*I52 | M52: 2.4 | N52: =B52*M52 | O52: =C52*M52 | P52: =D52*M52 | Q52: Lunch snack; ⚠ NUT
A53: Justin's Classic PB Squeeze Pack | B53: 3 | C53: 4 | D53: 3 | E53: 190 | F53: =B53*E53 | G53: =C53*E53 | H53: =D53*E53 | I53: 1.49 | J53: =B53*I53 | K53: =C53*I53 | L53: =D53*I53 | M53: 1.15 | N53: =B53*M53 | O53: =C53*M53 | P53: =D53*M53 | Q53: Lunch side; ⚠ NUT
A54: LUNCH Total | F54: =SUM(F49:F53) | G54: =SUM(G49:G53) | H54: =SUM(H49:H53) | J54: =SUM(J49:J53) | K54: =SUM(K49:K53) | L54: =SUM(L49:L53) | N54: =SUM(N49:N53) | O54: =SUM(O49:O53) | P54: =SUM(P49:P53)
A55: Sun Jul 26 — SUPPLEMENT
A56: Food Item | B56: Qty (Scout 3) | C56: Qty (Scout 4) | D56: Qty (Adult 3) | E56: kcal/unit | F56: Scout 3 kcal | G56: Scout 4 kcal | H56: Adult 3 kcal | I56: $/unit | J56: Scout 3 $ | K56: Scout 4 $ | L56: Adult 3 $ | M56: oz/unit | N56: Scout 3 oz | O56: Scout 4 oz | P56: Adult 3 oz | Q56: Notes
A57: Clif Builder's Bar (adult supplement) | B57: 0 | C57: 0 | D57: 3 | E57: 290 | F57: =B57*E57 | G57: =C57*E57 | H57: =D57*E57 | I57: 2.17 | J57: =B57*I57 | K57: =C57*I57 | L57: =D57*I57 | M57: 2.4 | N57: =B57*M57 | O57: =C57*M57 | P57: =D57*M57 | Q57: Adults only ★; ⚠ NUT
A58: Justin's PB Squeeze (adult supplement) | B58: 0 | C58: 0 | D58: 3 | E58: 190 | F58: =B58*E58 | G58: =C58*E58 | H58: =D58*E58 | I58: 1.49 | J58: =B58*I58 | K58: =C58*I58 | L58: =D58*I58 | M58: 1.15 | N58: =B58*M58 | O58: =C58*M58 | P58: =D58*M58 | Q58: Adults only ★; ⚠ NUT
A59: SUPPLEMENT Total | F59: =SUM(F57:F58) | G59: =SUM(G57:G58) | H59: =SUM(H57:H58) | J59: =SUM(J57:J58) | K59: =SUM(K57:K58) | L59: =SUM(L57:L58) | N59: =SUM(N57:N58) | O59: =SUM(O57:O58) | P59: =SUM(P57:P58)
A60: Sun Jul 26 — DINNER
A61: Food Item | B61: Qty (Scout 3) | C61: Qty (Scout 4) | D61: Qty (Adult 3) | E61: kcal/unit | F61: Scout 3 kcal | G61: Scout 4 kcal | H61: Adult 3 kcal | I61: $/unit | J61: Scout 3 $ | K61: Scout 4 $ | L61: Adult 3 $ | M61: oz/unit | N61: Scout 3 oz | O61: Scout 4 oz | P61: Adult 3 oz | Q61: Notes
A62: Peak Refuel – Beef Stroganoff | B62: 2 | C62: 3 | D62: 3 | E62: 600 | F62: =B62*E62 | G62: =C62*E62 | H62: =D62*E62 | I62: 7.49 | J62: =B62*I62 | K62: =C62*I62 | L62: =D62*I62 | M62: 3.5 | N62: =B62*M62 | O62: =C62*M62 | P62: =D62*M62 | Q62: Sun dinner (1.5 svgs/pouch)
A63: Mission Street Taco Flour Tortillas | B63: 6 | C63: 8 | D63: 6 | E63: 75 | F63: =B63*E63 | G63: =C63*E63 | H63: =D63*E63 | I63: 0.25 | J63: =B63*I63 | K63: =C63*I63 | L63: =D63*I63 | M63: 0.5 | N63: =B63*M63 | O63: =C63*M63 | P63: =D63*M63 | Q63: 2/person; nut-free ✓
A64: Idahoan Mashed Potatoes – Butter & Herb | B64: 3 | C64: 4 | D64: 3 | E64: 110 | F64: =B64*E64 | G64: =C64*E64 | H64: =D64*E64 | I64: 0.98 | J64: =B64*I64 | K64: =C64*I64 | L64: =D64*I64 | M64: 1 | N64: =B64*M64 | O64: =C64*M64 | P64: =D64*M64 | Q64: Dinner side
A65: Swiss Miss Hot Chocolate | B65: 6 | C65: 8 | D65: 0 | E65: 90 | F65: =B65*E65 | G65: =C65*E65 | H65: =D65*E65 | I65: 0.38 | J65: =B65*I65 | K65: =C65*I65 | L65: =D65*I65 | M65: 0.73 | N65: =B65*M65 | O65: =C65*M65 | P65: =D65*M65 | Q65: Scouts only (2 packets/person)
A66: DINNER Total | F66: =SUM(F62:F65) | G66: =SUM(G62:G65) | H66: =SUM(H62:H65) | J66: =SUM(J62:J65) | K66: =SUM(K62:K65) | L66: =SUM(L62:L65) | N66: =SUM(N62:N65) | O66: =SUM(O62:O65) | P66: =SUM(P62:P65)
A67: Sun Jul 26 — DESSERT
A68: Food Item | B68: Qty (Scout 3) | C68: Qty (Scout 4) | D68: Qty (Adult 3) | E68: kcal/unit | F68: Scout 3 kcal | G68: Scout 4 kcal | H68: Adult 3 kcal | I68: $/unit | J68: Scout 3 $ | K68: Scout 4 $ | L68: Adult 3 $ | M68: oz/unit | N68: Scout 3 oz | O68: Scout 4 oz | P68: Adult 3 oz | Q68: Notes
A69: Justin's Dark Chocolate Peanut Butter Cups | B69: 3 | C69: 4 | D69: 3 | E69: 210 | F69: =B69*E69 | G69: =C69*E69 | H69: =D69*E69 | I69: 1.49 | J69: =B69*I69 | K69: =C69*I69 | L69: =D69*I69 | M69: 1.41 | N69: =B69*M69 | O69: =C69*M69 | P69: =D69*M69 | Q69: 1 packet/person; ⚠ NUT
A70: Swiss Miss Hot Chocolate | B70: 6 | C70: 8 | D70: 0 | E70: 90 | F70: =B70*E70 | G70: =C70*E70 | H70: =D70*E70 | I70: 0.38 | J70: =B70*I70 | K70: =C70*I70 | L70: =D70*I70 | M70: 0.73 | N70: =B70*M70 | O70: =C70*M70 | P70: =D70*M70 | Q70: Scouts only (2 packets/person)
A71: DESSERT Total | F71: =SUM(F69:F70) | G71: =SUM(G69:G70) | H71: =SUM(H69:H70) | J71: =SUM(J69:J70) | K71: =SUM(K69:K70) | L71: =SUM(L69:L70) | N71: =SUM(N69:N70) | O71: =SUM(O69:O70) | P71: =SUM(P69:P70)
A72: DAY 2 (Sun Jul 26) TOTAL | F72: =SUM(F39,F46,F54,F59,F66,F71) | G72: =SUM(G39,G46,G54,G59,G66,G71) | H72: =SUM(H39,H46,H54,H59,H66,H71) | J72: =SUM(J39,J46,J54,J59,J66,J71) | K72: =SUM(K39,K46,K54,K59,K66,K71) | L72: =SUM(L39,L46,L54,L59,L66,L71) | N72: =SUM(N39,N46,N54,N59,N66,N71) | O72: =SUM(O39,O46,O54,O59,O66,O71) | P72: =SUM(P39,P46,P54,P59,P66,P71)
A74: MON JUL 27 — DAY 3 DETAILS
A75: Mon Jul 27 — BREAKFAST
A76: Food Item | B76: Qty (Scout 3) | C76: Qty (Scout 4) | D76: Qty (Adult 3) | E76: kcal/unit | F76: Scout 3 kcal | G76: Scout 4 kcal | H76: Adult 3 kcal | I76: $/unit | J76: Scout 3 $ | K76: Scout 4 $ | L76: Adult 3 $ | M76: oz/unit | N76: Scout 3 oz | O76: Scout 4 oz | P76: Adult 3 oz | Q76: Notes
A77: ProBar Meal – Oatmeal Chocolate Chip | B77: 3 | C77: 4 | D77: 3 | E77: 290 | F77: =B77*E77 | G77: =C77*E77 | H77: =D77*E77 | I77: 2.99 | J77: =B77*I77 | K77: =C77*I77 | L77: =D77*I77 | M77: 3 | N77: =B77*M77 | O77: =C77*M77 | P77: =D77*M77 | Q77: Bkfst · ⚠ NUT (cashews)
A78: Swiss Miss Hot Chocolate | B78: 6 | C78: 8 | D78: 0 | E78: 90 | F78: =B78*E78 | G78: =C78*E78 | H78: =D78*E78 | I78: 0.38 | J78: =B78*I78 | K78: =C78*I78 | L78: =D78*I78 | M78: 0.73 | N78: =B78*M78 | O78: =C78*M78 | P78: =D78*M78 | Q78: Scouts only (2 packets/person)
A79: Adults: own coffee / tea | B79: 0 | C79: 0 | D79: 3 | E79: 0 | F79: =B79*E79 | G79: =C79*E79 | H79: =D79*E79 | I79: 0 | J79: =B79*I79 | K79: =C79*I79 | L79: =D79*I79 | M79: 0 | N79: =B79*M79 | O79: =C79*M79 | P79: =D79*M79 | Q79: Adults only ★
A80: BREAKFAST Total | F80: =SUM(F77:F79) | G80: =SUM(G77:G79) | H80: =SUM(H77:H79) | J80: =SUM(J77:J79) | K80: =SUM(K77:K79) | L80: =SUM(L77:L79) | N80: =SUM(N77:N79) | O80: =SUM(O77:O79) | P80: =SUM(P77:P79)
A81: Mon Jul 27 — SNACKS
A82: Food Item | B82: Qty (Scout 3) | C82: Qty (Scout 4) | D82: Qty (Adult 3) | E82: kcal/unit | F82: Scout 3 kcal | G82: Scout 4 kcal | H82: Adult 3 kcal | I82: $/unit | J82: Scout 3 $ | K82: Scout 4 $ | L82: Adult 3 $ | M82: oz/unit | N82: Scout 3 oz | O82: Scout 4 oz | P82: Adult 3 oz | Q82: Notes
A83: Krave Sea Salt Original Beef Jerky | B83: 3 | C83: 4 | D83: 3 | E83: 140 | F83: =B83*E83 | G83: =C83*E83 | H83: =D83*E83 | I83: 2.19 | J83: =B83*I83 | K83: =C83*I83 | L83: =D83*I83 | M83: 1.48 | N83: =B83*M83 | O83: =C83*M83 | P83: =D83*M83 | Q83: Safe for nut allergy ✓
A84: Clif Bar – Crunchy PB | B84: 3 | C84: 4 | D84: 3 | E84: 250 | F84: =B84*E84 | G84: =C84*E84 | H84: =D84*E84 | I84: 1.29 | J84: =B84*I84 | K84: =C84*I84 | L84: =D84*I84 | M84: 2.4 | N84: =B84*M84 | O84: =C84*M84 | P84: =D84*M84 | Q84: ⚠ NUT
A85: Gatorade Powder Pack | B85: 3 | C85: 4 | D85: 3 | E85: 130 | F85: =B85*E85 | G85: =C85*E85 | H85: =D85*E85 | I85: 0.38 | J85: =B85*I85 | K85: =C85*I85 | L85: =D85*I85 | M85: 1.23 | N85: =B85*M85 | O85: =C85*M85 | P85: =D85*M85 | Q85: Electrolytes
A86: Peak Refuel – Fudge Brownie Bites | B86: 2 | C86: 2 | D86: 2 | E86: 450 | F86: =B86*E86 | G86: =C86*E86 | H86: =D86*E86 | I86: 4.99 | J86: =B86*I86 | K86: =C86*I86 | L86: =D86*I86 | M86: 1.5 | N86: =B86*M86 | O86: =C86*M86 | P86: =D86*M86 | Q86: Buddy-pair shares pouch
A87: SNACKS Total | F87: =SUM(F83:F86) | G87: =SUM(G83:G86) | H87: =SUM(H83:H86) | J87: =SUM(J83:J86) | K87: =SUM(K83:K86) | L87: =SUM(L83:L86) | N87: =SUM(N83:N86) | O87: =SUM(O83:O86) | P87: =SUM(P83:P86)
A88: Mon Jul 27 — LUNCH
A89: Food Item | B89: Qty (Scout 3) | C89: Qty (Scout 4) | D89: Qty (Adult 3) | E89: kcal/unit | F89: Scout 3 kcal | G89: Scout 4 kcal | H89: Adult 3 kcal | I89: $/unit | J89: Scout 3 $ | K89: Scout 4 $ | L89: Adult 3 $ | M89: oz/unit | N89: Scout 3 oz | O89: Scout 4 oz | P89: Adult 3 oz | Q89: Notes
A90: Columbus Hard Salami (sliced packet) | B90: 3 | C90: 4 | D90: 3 | E90: 110 | F90: =B90*E90 | G90: =C90*E90 | H90: =D90*E90 | I90: 2.99 | J90: =B90*I90 | K90: =C90*I90 | L90: =D90*I90 | M90: 2 | N90: =B90*M90 | O90: =C90*M90 | P90: =D90*M90 | Q90: Lunch; 1/person; nut-free
A91: Wasa Crisp'n Light Crackerbread | B91: 3 | C91: 4 | D91: 3 | E91: 60 | F91: =B91*E91 | G91: =C91*E91 | H91: =D91*E91 | I91: 0.5 | J91: =B91*I91 | K91: =C91*I91 | L91: =D91*I91 | M91: 1 | N91: =B91*M91 | O91: =C91*M91 | P91: =D91*M91 | Q91: Lunch side
A92: Mission Street Taco Flour Tortillas | B92: 6 | C92: 8 | D92: 6 | E92: 75 | F92: =B92*E92 | G92: =C92*E92 | H92: =D92*E92 | I92: 0.25 | J92: =B92*I92 | K92: =C92*I92 | L92: =D92*I92 | M92: 0.5 | N92: =B92*M92 | O92: =C92*M92 | P92: =D92*M92 | Q92: 2/person; nut-free ✓
A93: Tillamook Cheddar Cheese Packets | B93: 3 | C93: 4 | D93: 3 | E93: 90 | F93: =B93*E93 | G93: =C93*E93 | H93: =D93*E93 | I93: 0.75 | J93: =B93*I93 | K93: =C93*I93 | L93: =D93*I93 | M93: 0.7 | N93: =B93*M93 | O93: =C93*M93 | P93: =D93*M93 | Q93: 1/person; nut-free ✓
A94: Justin's Classic PB Squeeze Pack | B94: 3 | C94: 4 | D94: 3 | E94: 190 | F94: =B94*E94 | G94: =C94*E94 | H94: =D94*E94 | I94: 1.49 | J94: =B94*I94 | K94: =C94*I94 | L94: =D94*I94 | M94: 1.15 | N94: =B94*M94 | O94: =C94*M94 | P94: =D94*M94 | Q94: Lunch side; ⚠ NUT
A95: LUNCH Total | F95: =SUM(F90:F94) | G95: =SUM(G90:G94) | H95: =SUM(H90:H94) | J95: =SUM(J90:J94) | K95: =SUM(K90:K94) | L95: =SUM(L90:L94) | N95: =SUM(N90:N94) | O95: =SUM(O90:O94) | P95: =SUM(P90:P94)
A96: Mon Jul 27 — DINNER
A97: Food Item | B97: Qty (Scout 3) | C97: Qty (Scout 4) | D97: Qty (Adult 3) | E97: kcal/unit | F97: Scout 3 kcal | G97: Scout 4 kcal | H97: Adult 3 kcal | I97: $/unit | J97: Scout 3 $ | K97: Scout 4 $ | L97: Adult 3 $ | M97: oz/unit | N97: Scout 3 oz | O97: Scout 4 oz | P97: Adult 3 oz | Q97: Notes
A98: Peak Refuel – Beef Pasta Marinara | B98: 2 | C98: 3 | D98: 3 | E98: 780 | F98: =B98*E98 | G98: =C98*E98 | H98: =D98*E98 | I98: 7.49 | J98: =B98*I98 | K98: =C98*I98 | L98: =D98*I98 | M98: 3.2 | N98: =B98*M98 | O98: =C98*M98 | P98: =D98*M98 | Q98: Mon dinner (1.5 svgs/pouch)
A99: Mission Street Taco Flour Tortillas | B99: 6 | C99: 8 | D99: 6 | E99: 75 | F99: =B99*E99 | G99: =C99*E99 | H99: =D99*E99 | I99: 0.25 | J99: =B99*I99 | K99: =C99*I99 | L99: =D99*I99 | M99: 0.5 | N99: =B99*M99 | O99: =C99*M99 | P99: =D99*M99 | Q99: 2/person; nut-free ✓
A100: Tillamook Cheddar Cheese Packets | B100: 6 | C100: 8 | D100: 6 | E100: 90 | F100: =B100*E100 | G100: =C100*E100 | H100: =D100*E100 | I100: 0.75 | J100: =B100*I100 | K100: =C100*I100 | L100: =D100*I100 | M100: 0.7 | N100: =B100*M100 | O100: =C100*M100 | P100: =D100*M100 | Q100: 2/person; nut-free ✓
A101: Swiss Miss Hot Chocolate | B101: 6 | C101: 8 | D101: 0 | E101: 90 | F101: =B101*E101 | G101: =C101*E101 | H101: =D101*E101 | I101: 0.38 | J101: =B101*I101 | K101: =C101*I101 | L101: =D101*I101 | M101: 0.73 | N101: =B101*M101 | O101: =C101*M101 | P101: =D101*M101 | Q101: Scouts only (2 packets/person)
A102: DINNER Total | F102: =SUM(F98:F101) | G102: =SUM(G98:G101) | H102: =SUM(H98:H101) | J102: =SUM(J98:J101) | K102: =SUM(K98:K101) | L102: =SUM(L98:L101) | N102: =SUM(N98:N101) | O102: =SUM(O98:O101) | P102: =SUM(P98:P101)
A103: Mon Jul 27 — DESSERT
...

Sheet Shopping List
A1: Master Shopping List — 19 People · 6 Bear Cans | July 25–30, 2026
A2: 🟡 Yellow = bulk buy (Costco/Amazon) | 🟠 Orange = adult supplement | Group Total = 3*(Scout 3) + 1*(Scout 4) + 2*(Adult 3)
A3: ☐ | B3: Food Item | C3: Phase 1 Qty (Scout 3 Can) | D3: Phase 1 Qty (Scout 4 Can) | E3: Phase 1 Qty (Adult 3 Can) | F3: Phase 2 Qty (Scout 3 Can) | G3: Phase 2 Qty (Scout 4 Can) | H3: Phase 2 Qty (Adult 3 Can) | I3: Group Total (6 Days Packs) | J3: $/Unit | K3: Scout 3 Cost (6 Days) | L3: Scout 4 Cost (6 Days) | M3: Adult 3 Cost (6 Days) | N3: Group Total $ | O3: oz/unit | P3: Group ozs | Q3: Where to Buy
A4: ☐ | B4: 88 Acres Seed + Oat Bars (allergy scout) | C4: 0 | D4: 0 | E4: 0 | F4: 0 | G4: 0 | H4: 0 | I4: 6 | J4: 2.4 | K4: =(C4+F4)*J4 | L4: =(D4+G4)*J4 | M4: =(E4+H4)*J4 | N4: =I4*J4 | O4: 1.4 | P4: =I4*O4 | Q4: Allergy scout snacks swap
A5: ☐ | B5: Adults: own coffee / tea | C5: 0 | D5: 0 | E5: 6 | F5: 0 | G5: 0 | H5: 9 | I5: =3*(C5+F5)+1*(D5+G5)+2*(E5+H5) | J5: 0 | K5: =(C5+F5)*J5 | L5: =(D5+G5)*J5 | M5: =(E5+H5)*J5 | N5: =I5*J5 | O5: 0 | P5: =I5*O5 | Q5: Adults only ★
A6: ☐ | B6: Backpacker's Pantry – Crème Brûlée | C6: 4 | D6: 4 | E6: 4 | F6: 2 | G6: 2 | H6: 2 | I6: =3*(C6+F6)+1*(D6+G6)+2*(E6+H6) | J6: 8.99 | K6: =(C6+F6)*J6 | L6: =(D6+G6)*J6 | M6: =(E6+H6)*J6 | N6: =I6*J6 | O6: 2.26 | P6: =I6*O6 | Q6: Buddy-pair shares pouch
A7: ☐ | B7: Banana Chips (1 oz) | C7: 3 | D7: 4 | E7: 3 | F7: 3 | G7: 4 | H7: 3 | I7: =3*(C7+F7)+1*(D7+G7)+2*(E7+H7) | J7: 0.45 | K7: =(C7+F7)*J7 | L7: =(D7+G7)*J7 | M7: =(E7+H7)*J7 | N7: =I7*J7 | O7: 1 | P7: =I7*O7 | Q7: Nut-free ✓
A8: ☐ | B8: Chicken of the Sea Shredded Chicken Pouch | C8: 3 | D8: 4 | E8: 3 | F8: 3 | G8: 4 | H8: 3 | I8: =3*(C8+F8)+1*(D8+G8)+2*(E8+H8) | J8: 2.29 | K8: =(C8+F8)*J8 | L8: =(D8+G8)*J8 | M8: =(E8+H8)*J8 | N8: =I8*J8 | O8: 2.5 | P8: =I8*O8 | Q8: No cook; nut-free ✓
A9: ☐ | B9: Clif Bar – Crunchy PB | C9: 6 | D9: 8 | E9: 6 | F9: 6 | G9: 8 | H9: 6 | I9: =3*(C9+F9)+1*(D9+G9)+2*(E9+H9) | J9: 1.29 | K9: =(C9+F9)*J9 | L9: =(D9+G9)*J9 | M9: =(E9+H9)*J9 | N9: =I9*J9 | O9: 2.4 | P9: =I9*O9 | Q9: Lunch snack; ⚠ NUT
A10: ☐ | B10: Clif Builder's Bar (adult supplement) | C10: 0 | D10: 0 | E10: 3 | F10: 0 | G10: 0 | H10: 3 | I10: =3*(C10+F10)+1*(D10+G10)+2*(E10+H10) | J10: 2.17 | K10: =(C10+F10)*J10 | L10: =(D10+G10)*J10 | M10: =(E10+H10)*J10 | N10: =I10*J10 | O10: 2.4 | P10: =I10*O10 | Q10: Adults only ★; ⚠ NUT
A11: ☐ | B11: Columbus Hard Salami (sliced packet) | C11: 3 | D11: 4 | E11: 3 | F11: 3 | G11: 4 | H11: 3 | I11: =3*(C11+F11)+1*(D11+G11)+2*(E11+H11) | J11: 2.99 | K11: =(C11+F11)*J11 | L11: =(D11+G11)*J11 | M11: =(E11+H11)*J11 | N11: =I11*J11 | O11: 2 | P11: =I11*O11 | Q11: Lunch; 1/person; nut-free
A12: ☐ | B12: Gatorade Powder Pack | C12: 12 | D12: 16 | E12: 12 | F12: 12 | G12: 16 | H12: 12 | I12: =3*(C12+F12)+1*(D12+G12)+2*(E12+H12) | J12: 0.38 | K12: =(C12+F12)*J12 | L12: =(D12+G12)*J12 | M12: =(E12+H12)*J12 | N12: =I12*J12 | O12: 1.23 | P12: =I12*O12 | Q12: Electrolytes
A13: ☐ | B13: Honey Stinger Gold Waffle (allergy scout) | C13: 0 | D13: 0 | E13: 0 | F13: 0 | G13: 0 | H13: 0 | I13: 5 | J13: 1.09 | K13: =(C13+F13)*J13 | L13: =(D13+G13)*J13 | M13: =(E13+H13)*J13 | N13: =I13*J13 | O13: 1 | P13: =I13*O13 | Q13: Allergy scout dessert swap
A14: ☐ | B14: Idahoan Mashed Potatoes – Butter & Herb | C14: 3 | D14: 4 | E14: 3 | F14: 3 | G14: 4 | H14: 3 | I14: =3*(C14+F14)+1*(D14+G14)+2*(E14+H14) | J14: 0.98 | K14: =(C14+F14)*J14 | L14: =(D14+G14)*J14 | M14: =(E14+H14)*J14 | N14: =I14*J14 | O14: 1 | P14: =I14*O14 | Q14: Dinner side
A15: ☐ | B15: Justin's Classic PB Squeeze Pack | C15: 6 | D15: 8 | E15: 6 | F15: 6 | G15: 8 | H15: 6 | I15: =3*(C15+F15)+1*(D15+G15)+2*(E15+H15) | J15: 1.49 | K15: =(C15+F15)*J15 | L15: =(D15+G15)*J15 | M15: =(E15+H15)*J15 | N15: =I15*J15 | O15: 1.15 | P15: =I15*O15 | Q15: Lunch side; ⚠ NUT
A16: ☐ | B16: Justin's Dark Chocolate Peanut Butter Cups | C16: 3 | D16: 4 | E16: 3 | F16: 3 | G16: 4 | H16: 3 | I16: =3*(C16+F16)+1*(D16+G16)+2*(E16+H16) | J16: 1.49 | K16: =(C16+F16)*J16 | L16: =(D16+G16)*J16 | M16: =(E16+H16)*J16 | N16: =I16*J16 | O16: 1.41 | P16: =I16*O16 | Q16: 1 packet/person; ⚠ NUT
A17: ☐ | B17: Justin's PB Squeeze (adult supplement) | C17: 0 | D17: 0 | E17: 3 | F17: 0 | G17: 0 | H17: 3 | I17: =3*(C17+F17)+1*(D17+G17)+2*(E17+H17) | J17: 1.49 | K17: =(C17+F17)*J17 | L17: =(D17+G17)*J17 | M17: =(E17+H17)*J17 | N17: =I17*J17 | O17: 1.15 | P17: =I17*O17 | Q17: Adults only ★; ⚠ NUT
A18: ☐ | B18: Kind – Caramel Almond & Peanut Bar | C18: 3 | D18: 4 | E18: 3 | F18: 3 | G18: 4 | H18: 3 | I18: =3*(C18+F18)+1*(D18+G18)+2*(E18+H18) | J18: 1.59 | K18: =(C18+F18)*J18 | L18: =(D18+G18)*J18 | M18: =(E18+H18)*J18 | N18: =I18*J18 | O18: 1.4 | P18: =I18*O18 | Q18: ⚠ NUT: swap → 88 Acres bar
A19: ☐ | B19: Kind – Dark Choc Nuts & Sea Salt Bar | C19: 3 | D19: 4 | E19: 3 | F19: 3 | G19: 4 | H19: 3 | I19: =3*(C19+F19)+1*(D19+G19)+2*(E19+H19) | J19: 1.04 | K19: =(C19+F19)*J19 | L19: =(D19+G19)*J19 | M19: =(E19+H19)*J19 | N19: =I19*J19 | O19: 1.4 | P19: =I19*O19 | Q19: ⚠ NUT: swap → 88 Acres bar
A20: ☐ | B20: Kind – Peanut Butter Dark Chocolate Bar | C20: 3 | D20: 4 | E20: 3 | F20: 3 | G20: 4 | H20: 3 | I20: =3*(C20+F20)+1*(D20+G20)+2*(E20+H20) | J20: 1.04 | K20: =(C20+F20)*J20 | L20: =(D20+G20)*J20 | M20: =(E20+H20)*J20 | N20: =I20*J20 | O20: 1.4 | P20: =I20*O20 | Q20: ⚠ NUT: swap → 88 Acres bar
A21: ☐ | B21: Krave Sea Salt Original Beef Jerky | C21: 9 | D21: 12 | E21: 9 | F21: 9 | G21: 12 | H21: 9 | I21: =3*(C21+F21)+1*(D21+G21)+2*(E21+H21) | J21: 2.19 | K21: =(C21+F21)*J21 | L21: =(D21+G21)*J21 | M21: =(E21+H21)*J21 | N21: =I21*J21 | O21: 1.48 | P21: =I21*O21 | Q21: Safe for nut allergy ✓
A22: ☐ | B22: MET-Rx Big100 – Super Cookie Crunch | C22: 3 | D22: 4 | E22: 3 | F22: 6 | G22: 8 | H22: 6 | I22: =3*(C22+F22)+1*(D22+G22)+2*(E22+H22) | J22: 2.19 | K22: =(C22+F22)*J22 | L22: =(D22+G22)*J22 | M22: =(E22+H22)*J22 | N22: =I22*J22 | O22: 3.53 | P22: =I22*O22 | Q22: Bkfst · ⚠ NUT
A23: ☐ | B23: Mission Street Taco Flour Tortillas | C23: 30 | D23: 40 | E23: 30 | F23: 24 | G23: 32 | H23: 24 | I23: =3*(C23+F23)+1*(D23+G23)+2*(E23+H23) | J23: 0.25 | K23: =(C23+F23)*J23 | L23: =(D23+G23)*J23 | M23: =(E23+H23)*J23 | N23: =I23*J23 | O23: 0.5 | P23: =I23*O23 | Q23: 2/person; nut-free ✓
A24: ☐ | B24: Once Again Organic Sunflower Butter Squeeze | C24: 0 | D24: 0 | E24: 0 | F24: 0 | G24: 0 | H24: 0 | I24: 4 | J24: 1.5 | K24: =(C24+F24)*J24 | L24: =(D24+G24)*J24 | M24: =(E24+H24)*J24 | N24: =I24*J24 | O24: 1.15 | P24: =I24*O24 | Q24: Allergy scout PB swap
A25: ☐ | B25: Peak Refuel – Beef Pasta Marinara | C25: 4 | D25: 6 | E25: 6 | F25: 2 | G25: 3 | H25: 3 | I25: =3*(C25+F25)+1*(D25+G25)+2*(E25+H25) | J25: 7.49 | K25: =(C25+F25)*J25 | L25: =(D25+G25)*J25 | M25: =(E25+H25)*J25 | N25: =I25*J25 | O25: 3.2 | P25: =I25*O25 | Q25: Sat dinner (1.5 svgs/pouch)
A26: ☐ | B26: Peak Refuel – Beef Stroganoff | C26: 2 | D26: 3 | E26: 3 | F26: 2 | G26: 3 | H26: 3 | I26: =3*(C26+F26)+1*(D26+G26)+2*(E26+H26) | J26: 7.49 | K26: =(C26+F26)*J26 | L26: =(D26+G26)*J26 | M26: =(E26+H26)*J26 | N26: =I26*J26 | O26: 3.5 | P26: =I26*O26 | Q26: Sun dinner (1.5 svgs/pouch)
A27: ☐ | B27: Peak Refuel – Fudge Brownie Bites | C27: 2 | D27: 2 | E27: 2 | F27: 2 | G27: 2 | H27: 2 | I27: =3*(C27+F27)+1*(D27+G27)+2*(E27+H27) | J27: 4.99 | K27: =(C27+F27)*J27 | L27: =(D27+G27)*J27 | M27: =(E27+H27)*J27 | N27: =I27*J27 | O27: 1.5 | P27: =I27*O27 | Q27: Buddy-pair shares pouch
A28: ☐ | B28: ProBar Meal – Oatmeal Chocolate Chip | C28: 6 | D28: 8 | E28: 6 | F28: 6 | G28: 8 | H28: 6 | I28: =3*(C28+F28)+1*(D28+G28)+2*(E28+H28) | J28: 2.99 | K28: =(C28+F28)*J28 | L28: =(D28+G28)*J28 | M28: =(E28+H28)*J28 | N28: =I28*J28 | O28: 3 | P28: =I28*O28 | Q28: Lunch · ⚠ NUT (cashews)
A29: ☐ | B29: Swiss Miss Hot Chocolate | C29: 48 | D29: 64 | E29: 0 | F29: 42 | G29: 56 | H29: 0 | I29: =3*(C29+F29)+1*(D29+G29)+2*(E29+H29) | J29: 0.38 | K29: =(C29+F29)*J29 | L29: =(D29+G29)*J29 | M29: =(E29+H29)*J29 | N29: =I29*J29 | O29: 0.73 | P29: =I29*O29 | Q29: Scouts only (2 packets/person)
A30: ☐ | B30: Tillamook Cheddar Cheese Packets | C30: 18 | D30: 24 | E30: 18 | F30: 12 | G30: 16 | H30: 12 | I30: =3*(C30+F30)+1*(D30+G30)+2*(E30+H30) | J30: 0.75 | K30: =(C30+F30)*J30 | L30: =(D30+G30)*J30 | M30: =(E30+H30)*J30 | N30: =I30*J30 | O30: 0.7 | P30: =I30*O30 | Q30: 2/person; nut-free ✓
A31: ☐ | B31: Trader Joe's Dried Mango Slices (1 oz) | C31: 3 | D31: 4 | E31: 3 | F31: 3 | G31: 4 | H31: 3 | I31: =3*(C31+F31)+1*(D31+G31)+2*(E31+H31) | J31: 0.55 | K31: =(C31+F31)*J31 | L31: =(D31+G31)*J31 | M31: =(E31+H31)*J31 | N31: =I31*J31 | O31: 1 | P31: =I31*O31 | Q31: TJ's — Sat snack · nut-free ✓
A32: ☐ | B32: Wasa Crisp'n Light Crackerbread | C32: 3 | D32: 4 | E32: 3 | F32: 3 | G32: 4 | H32: 3 | I32: =3*(C32+F32)+1*(D32+G32)+2*(E32+H32) | J32: 0.5 | K32: =(C32+F32)*J32 | L32: =(D32+G32)*J32 | M32: =(E32+H32)*J32 | N32: =I32*J32 | O32: 1 | P32: =I32*O32 | Q32: Lunch side
B33: Grand Total | K33: =SUM(K4:K32) | L33: =SUM(L4:L32) | M33: =SUM(M4:M32) | N33: =SUM(N4:N32) | P33: =SUM(P4:P32)

Sheet Packing List
A1: EMIGRANT WILDERNESS — BEAR CAN PACKING LIST · July 25–30, 2026
A2: Check off each item as you pack. ★ = adult supplement. Qty = items per bear can type.
A4: Packed | B4: Meal | C4: Item | D4: Scout Can (3 ppl) Qty | E4: Scout Can (4 ppl) Qty | F4: Adult Can (3 ppl) Qty | G4: Notes
A5: PHASE 1 — INITIAL CARRY (DAYS 1–3) — PACK AT TRAILHEAD
A6: SATURDAY JUL 25 — DAY 1
A7: ☐ | B7: SNACKS | C7: Kind – Peanut Butter Dark Chocolate Bar | D7: 3 | E7: 4 | F7: 3 | G7: hip-belt pocket; ⚠ NUT
A8: ☐ | B8: SNACKS | C8: Kind – Caramel Almond & Peanut Bar | D8: 3 | E8: 4 | F8: 3 | G8: hip-belt pocket; ⚠ NUT
A9: ☐ | B9: SNACKS | C9: Krave Sea Salt Original Beef Jerky | D9: 3 | E9: 4 | F9: 3 | G9: hip-belt pocket; nut-free
A10: ☐ | B10: SNACKS | C10: Gatorade Powder Pack | D10: 3 | E10: 4 | F10: 3 | G10: hip-belt pocket; electrolytes
A11: ☐ | B11: SNACKS | C11: Trader Joe's Dried Mango Slices (1 oz) | D11: 3 | E11: 4 | F11: 3 | G11: hip-belt pocket; nut-free
A12: ☐ | B12: LUNCH | C12: ProBar Meal – Oatmeal Chocolate Chip | D12: 3 | E12: 4 | F12: 3 | G12: no cook; ⚠ NUT
A13: ☐ | B13: DINNER | C13: Peak Refuel – Beef Pasta Marinara | D13: 2 | E13: 3 | F13: 3 | G13: hot · 1.5 svgs/pouch
A14: ☐ | B14: DINNER | C14: Flour Tortillas | D14: 6 | E14: 8 | F14: 6 | G14: dinner wraps + side
A15: ☐ | B15: DINNER | C15: Tillamook Cheddar Cheese Packets | D15: 6 | E15: 8 | F15: 6 | G15: dinner side
A16: ☐ | B16: DINNER | C16: Swiss Miss Hot Chocolate | D16: 6 | E16: 8 | F16: 0 | G16: scouts only
A17: ☐ | B17: DESSERT | C17: Backpacker's Pantry Crème Brûlée | D17: 2 | E17: 2 | F17: 2 | G17: hot · buddy-pair shares pouch
A18: ☐ | B18: DESSERT | C18: Swiss Miss Hot Chocolate | D18: 6 | E18: 8 | F18: 0 | G18: scouts only
A19: SUNDAY JUL 26 — DAY 2
A20: ☐ | B20: BREAKFAST | C20: MET-Rx Big100 – Super Cookie Crunch | D20: 3 | E20: 4 | F20: 3 | G20: grab & go; ⚠ NUT
A21: ☐ | B21: BREAKFAST | C21: Swiss Miss Hot Chocolate | D21: 6 | E21: 8 | F21: 0 | G21: scouts only
A22: ☐ | B22: BREAKFAST | C22: Adults: own coffee / tea | D22: 0 | E22: 0 | F22: 3 | G22: adults only ★
A23: ☐ | B23: SNACKS | C23: Krave Sea Salt Original Beef Jerky | D23: 3 | E23: 4 | F23: 3 | G23: hip-belt pocket; nut-free
A24: ☐ | B24: SNACKS | C24: Kind – Dark Choc Nuts & Sea Salt Bar | D24: 3 | E24: 4 | F24: 3 | G24: hip-belt pocket; ⚠ NUT
A25: ☐ | B25: SNACKS | C25: Gatorade Powder Pack | D25: 6 | E25: 8 | F25: 6 | G25: ×2/person; climb day
A26: ☐ | B26: SNACKS | C26: Banana Chips (1 oz) | D26: 3 | E26: 4 | F26: 3 | G26: nut-free
A27: ☐ | B27: LUNCH | C27: Chicken of the Sea Shredded Chicken Pouch | D27: 3 | E27: 4 | F27: 3 | G27: no cook; nut-free
A28: ☐ | B28: LUNCH | C28: Flour Tortillas | D28: 6 | E28: 8 | F28: 6 | G28: lunch wraps
A29: ☐ | B29: LUNCH | C29: Tillamook Cheddar Cheese Packets | D29: 3 | E29: 4 | F29: 3 | G29: lunch side
A30: ☐ | B30: LUNCH | C30: Clif Bar – Crunchy PB | D30: 3 | E30: 4 | F30: 3 | G30: lunch snack; ⚠ NUT
A31: ☐ | B31: LUNCH | C31: Justin's Classic PB Squeeze Pack | D31: 3 | E31: 4 | F31: 3 | G31: lunch side; ⚠ NUT
... A39: ☐ | B39: DESSERT | C39: Swiss Miss Hot Chocolate | D39: 6 | E39: 8 | F39: 0 | G39: scouts only
A40: MONDAY JUL 27 — DAY 3
A41: ☐ | B41: BREAKFAST | C41: ProBar Meal – Oatmeal Chocolate Chip | D41: 3 | E41: 4 | F41: 3 | G41: grab & go; ⚠ NUT (cashews)
A42: ☐ | B42: BREAKFAST | C42: Swiss Miss Hot Chocolate | D42: 6 | E42: 8 | F42: 0 | G42: scouts only
A43: ☐ | B43: BREAKFAST | C43: Adults: own coffee / tea | D43: 0 | E43: 0 | F43: 3 | G43: adults only ★
A44: ☐ | B44: SNACKS | C44: Krave Sea Salt Original Beef Jerky | D44: 3 | E44: 4 | F44: 3 | G44: hip-belt pocket; nut-free
A45: ☐ | B45: SNACKS | C45: Clif Bar – Crunchy PB | D45: 3 | E45: 4 | F45: 3 | G45: hip-belt pocket; ⚠ NUT
A46: ☐ | B46: SNACKS | C46: Gatorade Powder Pack | D46: 3 | E46: 4 | F46: 3 | G46: hip-belt pocket; electrolytes
A47: ☐ | B47: SNACKS | C47: Peak Refuel – Fudge Brownie Bites | D47: 2 | E47: 2 | F47: 2 | G47: morale afternoon snack; nut-free
A48: ☐ | B48: LUNCH | C48: Columbus Hard Salami (packet) | D48: 3 | E48: 4 | F48: 3 | G48: no cook; nut-free
A49: ☐ | B49: LUNCH | C49: Wasa Crispbread | D49: 3 | E49: 4 | F49: 3 | G49: no cook; nut-free
A50: ☐ | B50: LUNCH | C50: Flour Tortillas | D50: 6 | E50: 8 | F50: 6 | G50: lunch wraps
A51: ☐ | B51: LUNCH | C51: Tillamook Cheddar Cheese Packets | D51: 3 | E51: 4 | F51: 3 | G51: lunch side
A52: ☐ | B52: LUNCH | C52: Justin's Classic PB Squeeze Pack | D52: 3 | E52: 4 | F52: 3 | G52: lunch side; ⚠ NUT
... A58: ☐ | B58: DESSERT | C58: Swiss Miss Hot Chocolate | D58: 6 | E58: 8 | F58: 0 | G58: scouts only
A59: PHASE 2 — MULE DROP (DAYS 4–6) — REFILL CANS IN FIELD
A60: TUESDAY JUL 28 — DAY 4
A61: ☐ | B61: BREAKFAST | C61: MET-Rx Big100 – Super Cookie Crunch | D61: 3 | E61: 4 | F61: 3 | G61: grab & go; ⚠ NUT
A62: ☐ | B62: BREAKFAST | C62: Swiss Miss Hot Chocolate | D62: 6 | E62: 8 | F62: 0 | G62: scouts only
A63: ☐ | B63: BREAKFAST | C63: Adults: own coffee / tea | D63: 0 | E63: 0 | F63: 3 | G63: adults only ★
A64: ☐ | B64: SNACKS | C64: Krave Sea Salt Original Beef Jerky | D64: 3 | E64: 4 | F64: 3 | G64: hip-belt pocket; nut-free
A65: ☐ | B65: SNACKS | C65: Kind – Dark Choc Nuts & Sea Salt Bar | D65: 3 | E65: 4 | F65: 3 | G65: hip-belt pocket; ⚠ NUT
A66: ☐ | B66: SNACKS | C66: Gatorade Powder Pack | D66: 6 | E66: 8 | F66: 6 | G66: ×2/person; climb day
A67: ☐ | B67: SNACKS | C67: Banana Chips (1 oz) | D67: 3 | E67: 4 | F67: 3 | G67: nut-free
A68: ☐ | B68: LUNCH | C68: ProBar Meal – Oatmeal Chocolate Chip | D68: 3 | E68: 4 | F68: 3 | G68: no cook; ⚠ NUT
A69: ☐ | B69: DINNER | C69: Peak Refuel – Beef Stroganoff | D69: 2 | E69: 3 | F69: 3 | G69: hot · 1.5 svgs/pouch
A70: ☐ | B70: DINNER | C70: Flour Tortillas | D70: 6 | E70: 8 | F70: 6 | G70: dinner wraps
A71: ☐ | B71: DINNER | C71: Idahoan Mashed Potatoes | D71: 3 | E71: 4 | F71: 3 | G71: dinner side
A72: ☐ | B72: DINNER | C72: Swiss Miss Hot Chocolate | D72: 6 | E72: 8 | F72: 0 | G72: scouts only
... A74: ☐ | B74: DESSERT | C74: Swiss Miss Hot Chocolate | D74: 6 | E74: 8 | F74: 0 | G74: scouts only
A75: WEDNESDAY JUL 29 — DAY 5
A76: ☐ | B76: BREAKFAST | C76: ProBar Meal – Oatmeal Chocolate Chip | D76: 3 | E76: 4 | F76: 3 | G76: grab & go; ⚠ NUT (cashews)
A77: ☐ | B77: BREAKFAST | C77: Swiss Miss Hot Chocolate | D77: 6 | E77: 8 | F77: 0 | G77: scouts only
A78: ☐ | B78: BREAKFAST | C78: Adults: own coffee / tea | D78: 0 | E78: 0 | F78: 3 | G78: adults only ★
A79: ☐ | B79: SNACKS | C79: Kind – Peanut Butter Dark Chocolate Bar | D79: 3 | E79: 4 | F79: 3 | G79: hip-belt pocket; ⚠ NUT
A80: ☐ | B80: SNACKS | C80: Kind – Caramel Almond & Peanut Bar | D80: 3 | E80: 4 | F80: 3 | G80: hip-belt pocket; ⚠ NUT
A81: ☐ | B81: SNACKS | C81: Krave Sea Salt Original Beef Jerky | D81: 3 | E81: 4 | F81: 3 | G81: hip-belt pocket; nut-free
A82: ☐ | B82: SNACKS | C82: Gatorade Powder Pack | D82: 3 | E82: 4 | F82: 3 | G82: hip-belt pocket; electrolytes
A83: ☐ | B83: SNACKS | C83: Trader Joe's Dried Mango Slices (1 oz) | D83: 3 | E83: 4 | F83: 3 | G83: hip-belt pocket; nut-free
A84: ☐ | B84: LUNCH | C84: Chicken of the Sea Shredded Chicken Pouch | D84: 3 | E84: 4 | F84: 3 | G84: no cook; nut-free
A85: ☐ | B85: LUNCH | C85: Flour Tortillas | D85: 6 | E85: 8 | F85: 6 | G85: lunch wraps
A86: ☐ | B86: LUNCH | C86: Tillamook Cheddar Cheese Packets | D86: 3 | E86: 4 | F86: 3 | G86: lunch side
A87: ☐ | B87: LUNCH | C87: Clif Bar – Crunchy PB | D87: 3 | E87: 4 | F87: 3 | G87: lunch snack; ⚠ NUT
... A96: ☐ | B96: DESSERT | C96: Swiss Miss Hot Chocolate | D96: 6 | E96: 8 | F96: 0 | G96: scouts only
A97: THURSDAY JUL 30 — DAY 6
A98: ☐ | B98: BREAKFAST | C98: MET-Rx Big100 – Super Cookie Crunch | D98: 3 | E98: 4 | F98: 3 | G98: grab & go; ⚠ NUT
A99: ☐ | B99: BREAKFAST | C99: Swiss Miss Hot Chocolate | D99: 6 | E99: 8 | F99: 0 | G99: scouts only
A100: ☐ | B100: BREAKFAST | C100: Adults: own coffee / tea | D100: 0 | E100: 0 | F100: 3 | G100: adults only ★
A101: ☐ | B101: SNACKS | C101: Krave Sea Salt Original Beef Jerky | D101: 3 | E101: 4 | F101: 3 | G101: hip-belt pocket; nut-free
A102: ☐ | B102: SNACKS | C102: Clif Bar – Crunchy PB | D102: 3 | E102: 4 | F102: 3 | G102: hip-belt pocket; ⚠ NUT
A103: ☐ | B103: SNACKS | C103: Gatorade Powder Pack | D103: 3 | E103: 4 | F103: 3 | G103: hip-belt pocket; electrolytes
A104: ☐ | B104: SNACKS | C104: Peak Refuel – Fudge Brownie Bites | D104: 2 | E104: 2 | F104: 2 | G104: morale afternoon snack; nut-free
A105: ☐ | B105: LUNCH | C105: Columbus Hard Salami (packet) | D105: 3 | E105: 4 | F105: 3 | G105: no cook; nut-free
A106: ☐ | B106: LUNCH | C106: Wasa Crispbread | D106: 3 | E106: 4 | F106: 3 | G106: no cook; nut-free
A107: ☐ | B107: LUNCH | C107: Flour Tortillas | D107: 6 | E107: 8 | F107: 6 | G107: lunch wraps
A108: ☐ | B108: LUNCH | C108: Tillamook Cheddar Cheese Packets | D108: 3 | E108: 4 | F108: 3 | G108: lunch side
A109: ☐ | B109: LUNCH | C109: Justin's Classic PB Squeeze Pack | D109: 3 | E109: 4 | F109: 3 | G109: lunch side; ⚠ NUT

Sheet Nut Allergy — Scout Pack
A1: Nut Allergy Accommodation — Individual Scout Carry Pack (6 Days)
A2: Pre-pack all items in a labelled zip-lock or dry bag for this scout. They carry it personally and swap at each nut-item moment. Main canisters are UNCHANGED.
A4: Day | B4: Meal | C4: Remove (has nuts) | D4: Nuts in it | E4: Replace with | F4: Why safe | G4: kcal | H4: Where to buy
A5: Sat Jul 25 | B5: Snacks | C5: Kind PB Dark Choc Bar | D5: Peanuts, almonds | E5: 88 Acres Dark Choc Sea Salt Seed + Oat Bar | F5: Dedicated nut-free bakery. Free from top 9. | G5: 150 | H5: Amazon / 88acres.com
A6: Sat Jul 25 | B6: Snacks | C6: Kind – Caramel Almond & Peanut Bar | D6: Almonds, peanuts | E6: 88 Acres Cinnamon Maple Seed + Oat Bar | F6: Same nut-free facility. | G6: 150 | H6: Amazon / 88acres.com
A7: Sat Jul 25 | B7: Dessert | C7: BP Crème Brûlée | D7: Check label - may contain cashews | E7: Honey Stinger Gold Waffle (contingency) | F7: Honey Stinger: simple ingredients, no nuts. | G7: 160 | H7: REI / Amazon
A8: Sun Jul 26 | B8: Breakfast | C8: MET-Rx Big100 Super Cookie Crunch | D8: Peanuts, almonds, tree nuts | E8: No Nuts! Chocolate Chip Protein Bar | F8: Certified 100% nut-free facility. 12g protein. | G8: 185 | H8: Amazon / gononuts.com
A9: Sun Jul 26 | B9: Snacks | C9: Kind – Dark Choc Nuts & Sea Salt Bar | D9: Almonds, peanuts, cashews | E9: 88 Acres bar (any flavor) | F9: Same nut-free facility. | G9: 150 | H9: Amazon / 88acres.com
A10: Sun Jul 26 | B10: Lunch | C10: Clif Bar – Crunchy PB | D10: Peanuts | E10: Clif Bar – Chocolate Chip | F10: Clif Chocolate Chip: no nuts in ingredients. | G10: 250 | H10: Add to main Costco order
A11: Sun Jul 26 | B11: Lunch | C11: Justin's Classic PB Squeeze Pack | D11: Peanuts | E11: Once Again Sunflower Butter Squeeze Pack | F11: Peanut-free facility. Free from top 9. | G11: 200 | H11: Amazon
A12: Sun Jul 26 | B12: Dessert | C12: Justin's Dark Choc PB Cups | D12: Peanuts, almonds | E12: Honey Stinger Gold Waffle or Enjoy Life Choc | F12: No nuts. Enjoy Life: top-14 free. | G12: 160 | H12: REI / Amazon
A13: Mon Jul 27 | B13: Breakfast | C13: ProBar Meal – Oatmeal Chocolate Chip | D13: Cashews | E13: No Nuts! Cinnamon Roll or Caramel Mocha | F13: Same certified nut-free facility. | G13: 185 | H13: Amazon / gononuts.com
A14: Mon Jul 27 | B14: Snacks | C14: Clif Bar – Crunchy PB | D14: Peanuts | E14: Clif Bar – Chocolate Chip | F14: Clif Chocolate Chip: no nuts in ingredients. | G14: 250 | H14: Add to main Costco order
A15: Mon Jul 27 | B15: Lunch | C15: Justin's Classic PB Squeeze Pack | D15: Peanuts | E15: Once Again Sunflower Butter Squeeze Pack | F15: Peanut-free facility. Free from top 9. | G15: 200 | H15: Amazon
A16: Tue Jul 28 | B16: Breakfast | C16: MET-Rx Big100 Super Cookie Crunch | D16: Peanuts, almonds, tree nuts | E16: No Nuts! Chocolate Chip Protein Bar | F16: Certified 100% nut-free facility. | G16: 185 | H16: Amazon
... A27: Thu Jul 30 | B27: Lunch | C27: Justin's Classic PB Squeeze Pack | D27: Peanuts | E27: Once Again Sunflower Butter Squeeze Pack | F27: Peanut-free facility. | G27: 200 | H27: Amazon
